Workbook

Sheet Executive_Dashboard
A1: Portfolio Project: Retail & Logistics Operations Analysis
A2: Built by Ahmad Yasser Morsy | Core Focus: E-Commerce Fulfillment, Channel Margin & Delay Reduction
A4: Total GMV | B4: Total Net Profit | C4: Blended Net Margin % | D4: Total Orders | E4: SLA On-Time Delivery Rate % | F4: Total Units Sold
A5: =SUM(Transactions_Model!O2:O16) -> 7027.08 | B5: =SUM(Transactions_Model!P2:P16) -> 3822.58 | C5: =B5/A5 -> 0.54397844 | D5: =COUNTA(Transactions_Model!A2:A16) -> 15 | E5: =COUNTIF(Transactions_Model!N2:N16, "<=0")/D5 -> 0.73333333 | F5: =SUM(Transactions_Model!F2:F16) -> 201
A8: Channel | B8: Total Orders | C8: GMV | D8: Net Profit | E8: Net Margin % | F8: Return Rate % | G8: Primary Takeaway
A9: Direct Online | B9: =COUNTIF(Transactions_Model!$C$2:$C$16, A9) -> 6 | C9: =SUMIFS(Transactions_Model!$O$2:$O$16, Transactions_Model!$C$2:$C$16, A9) -> 287.43 | D9: =SUMIFS(Transactions_Model!$P$2:$P$16, Transactions_Model!$C$2:$C$16, A9) -> 110.43 | E9: =IFERROR(D9/C9, 0) -> 0.38419789 | F9: =COUNTIFS(Transactions_Model!$C$2:$C$16, A9, Transactions_Model!$J$2:$J$16, "Returned")/B9 -> 0.33333333 | G9: Highest margin, but needs volume growth.
A10: Marketplace | B10: =COUNTIF(Transactions_Model!$C$2:$C$16, A10) -> 5 | C10: =SUMIFS(Transactions_Model!$O$2:$O$16, Transactions_Model!$C$2:$C$16, A10) -> 339.95 | D10: =SUMIFS(Transactions_Model!$P$2:$P$16, Transactions_Model!$C$2:$C$16, A10) -> 202.45 | E10: =IFERROR(D10/C10, 0) -> 0.59552875 | F10: =COUNTIFS(Transactions_Model!$C$2:$C$16, A10, Transactions_Model!$J$2:$J$16, "Returned")/B10 -> 0 | G10: Good volume, but SLA risks are higher.
A11: B2B Wholesale | B11: =COUNTIF(Transactions_Model!$C$2:$C$16, A11) -> 4 | C11: =SUMIFS(Transactions_Model!$O$2:$O$16, Transactions_Model!$C$2:$C$16, A11) -> 6399.7 | D11: =SUMIFS(Transactions_Model!$P$2:$P$16, Transactions_Model!$C$2:$C$16, A11) -> 3509.7 | E11: =IFERROR(D11/C11, 0) -> 0.54841633 | F11: =COUNTIFS(Transactions_Model!$C$2:$C$16, A11, Transactions_Model!$J$2:$J$16, "Returned")/B11 -> 0 | G11: Strong revenue driver, low return rate.
A14: Region/Hub | B14: Shipments | C14: Avg Transit Days | D14: On-Time % | E14: Delay Risk Tier | F14: Actionable Recommendation
A15: REG-CAI | B15: =COUNTIF(Transactions_Model!$K$2:$K$16, A15) -> 5 | C15: =AVERAGEIF(Transactions_Model!$K$2:$K$16, A15, Transactions_Model!$L$2:$L$16) -> 1.8 | D15: =COUNTIFS(Transactions_Model!$K$2:$K$16, A15, Transactions_Model!$N$2:$N$16, "<=0")/B15 -> 1 | E15: =IF(D15<0.8, "High Risk", IF(D15<0.9, "Medium Risk", "Low Risk")) -> Low Risk | F15: Maintain current courier contracts.
A16: REG-ALX | B16: =COUNTIF(Transactions_Model!$K$2:$K$16, A16) -> 4 | C16: =AVERAGEIF(Transactions_Model!$K$2:$K$16, A16, Transactions_Model!$L$2:$L$16) -> 3 | D16: =COUNTIFS(Transactions_Model!$K$2:$K$16, A16, Transactions_Model!$N$2:$N$16, "<=0")/B16 -> 0.75 | E16: =IF(D16<0.8, "High Risk", IF(D16<0.9, "Medium Risk", "Low Risk")) -> High Risk | F16: Monitor closely; slight delays observed.
A17: REG-CAN | B17: =COUNTIF(Transactions_Model!$K$2:$K$16, A17) -> 3 | C17: =AVERAGEIF(Transactions_Model!$K$2:$K$16, A17, Transactions_Model!$L$2:$L$16) -> 4.3333333 | D17: =COUNTIFS(Transactions_Model!$K$2:$K$16, A17, Transactions_Model!$N$2:$N$16, "<=0")/B17 -> 0.66666667 | E17: =IF(D17<0.8, "High Risk", IF(D17<0.9, "Medium Risk", "Low Risk")) -> High Risk | F17: Renegotiate SLA terms with regional carrier.
A18: REG-UPP | B18: =COUNTIF(Transactions_Model!$K$2:$K$16, A18) -> 3 | C18: =AVERAGEIF(Transactions_Model!$K$2:$K$16, A18, Transactions_Model!$L$2:$L$16) -> 6 | D18: =COUNTIFS(Transactions_Model!$K$2:$K$16, A18, Transactions_Model!$N$2:$N$16, "<=0")/B18 -> 0.33333333 | E18: =IF(D18<0.8, "High Risk", IF(D18<0.9, "Medium Risk", "Low Risk")) -> High Risk | F18: Consider local fulfillment hub to reduce transit.
A21: Executive Takeaways & Action Plan
A22: 1. Margin Leakage: High discount rates in B2B Wholesale are impacting overall profitability.
A23: 2. Courier SLA Renegotiation: Upper Egypt (REG-UPP) consistently misses SLA targets, requiring immediate courier review.
A24: 3. Stock Rebalancing: High return rates in Marketplace channel suggest product quality or listing accuracy issues.

Sheet Transactions_Model
A1: Order_ID | B1: Order_Date | C1: Channel | D1: SKU | E1: Category | F1: Units_Sold | G1: Unit_List_Price | H1: Unit_Cost | I1: Discount_Amt | J1: Order_Status | K1: Shipping_Region | L1: Transit_Days | M1: Promised_Days | N1: Delay_Variance | O1: Net_Revenue | P1: Gross_Profit | Q1: Notes_Annotations
A2: ORD-1001 | B2: 45200 | C2: Direct Online | D2: SKU-101 | E2: {=_xlfn.XLOOKUP(D2, Lookup_Dimensions!$A$2:$A$8, Lookup_Dimensions!$B$2:$B$8, "Unknown")} -> Electronics | F2: 2 | G2: 39.99 | H2: {=_xlfn.XLOOKUP(D2, Lookup_Dimensions!$A$2:$A$8, Lookup_Dimensions!$D$2:$D$8, 0)} -> 18.5 | I2: 0 | J2: Delivered | K2: REG-CAI | L2: 2 | M2: {=_xlfn.XLOOKUP(K2, Lookup_Dimensions!$H$2:$H$5, Lookup_Dimensions!$J$2:$J$5, 0)} -> 2 | N2: =L2-M2 -> 0 | O2: =IF(J2="Returned", 0, F2*G2 - I2) -> 79.98 | P2: =O2 - (F2*H2) -> 42.98 | Q2: Standard delivery
A3: ORD-1002 | B3: 45201 | C3: Marketplace | D3: SKU-102 | E3: {=_xlfn.XLOOKUP(D3, Lookup_Dimensions!$A$2:$A$8, Lookup_Dimensions!$B$2:$B$8, "Unknown")} -> Electronics | F3: 1 | G3: 89.99 | H3: {=_xlfn.XLOOKUP(D3, Lookup_Dimensions!$A$2:$A$8, Lookup_Dimensions!$D$2:$D$8, 0)} -> 42 | I3: 10 | J3: Delivered | K3: REG-ALX | L3: 4 | M3: {=_xlfn.XLOOKUP(K3, Lookup_Dimensions!$H$2:$H$5, Lookup_Dimensions!$J$2:$J$5, 0)} -> 3 | N3: =L3-M3 -> 1 | O3: =IF(J3="Returned", 0, F3*G3 - I3) -> 79.99 | P3: =O3 - (F3*H3) -> 37.99 | Q3: Delayed by courier
A4: ORD-1003 | B4: 45202 | C4: B2B Wholesale | D4: SKU-107 | E4: {=_xlfn.XLOOKUP(D4, Lookup_Dimensions!$A$2:$A$8, Lookup_Dimensions!$B$2:$B$8, "Unknown")} -> Home & Storage | F4: 50 | G4: 34 | H4: {=_xlfn.XLOOKUP(D4, Lookup_Dimensions!$A$2:$A$8, Lookup_Dimensions!$D$2:$D$8, 0)} -> 14 | I4: 100 | J4: Delivered | K4: REG-CAN | L4: 4 | M4: {=_xlfn.XLOOKUP(K4, Lookup_Dimensions!$H$2:$H$5, Lookup_Dimensions!$J$2:$J$5, 0)} -> 4 | N4: =L4-M4 -> 0 | O4: =IF(J4="Returned", 0, F4*G4 - I4) -> 1600 | P4: =O4 - (F4*H4) -> 900 | Q4: Bulk order
A5: ORD-1004 | B5: 45203 | C5: Direct Online | D5: SKU-103 | E5: {=_xlfn.XLOOKUP(D5, Lookup_Dimensions!$A$2:$A$8, Lookup_Dimensions!$B$2:$B$8, "Unknown")} -> Apparel | F5: 1 | G5: 45 | H5: {=_xlfn.XLOOKUP(D5, Lookup_Dimensions!$A$2:$A$8, Lookup_Dimensions!$D$2:$D$8, 0)} -> 15 | I5: 0 | J5: Returned | K5: REG-CAI | L5: 2 | M5: {=_xlfn.XLOOKUP(K5, Lookup_Dimensions!$H$2:$H$5, Lookup_Dimensions!$J$2:$J$5, 0)} -> 2 | N5: =L5-M5 -> 0 | O5: =IF(J5="Returned", 0, F5*G5 - I5) -> 0 | P5: =O5 - (F5*H5) -> -15 | Q5: Customer changed mind
A6: ORD-1005 | B6: 45204 | C6: Marketplace | D6: SKU-104 | E6: {=_xlfn.XLOOKUP(D6, Lookup_Dimensions!$A$2:$A$8, Lookup_Dimensions!$B$2:$B$8, "Unknown")} -> Apparel | F6: 3 | G6: 24.99 | H6: {=_xlfn.XLOOKUP(D6, Lookup_Dimensions!$A$2:$A$8, Lookup_Dimensions!$D$2:$D$8, 0)} -> 8.5 | I6: 5 | J6: Delivered | K6: REG-UPP | L6: 6 | M6: {=_xlfn.XLOOKUP(K6, Lookup_Dimensions!$H$2:$H$5, Lookup_Dimensions!$J$2:$J$5, 0)} -> 5 | N6: =L6-M6 -> 1 | O6: =IF(J6="Returned", 0, F6*G6 - I6) -> 69.97 | P6: =O6 - (F6*H6) -> 44.47 | Q6: Weather delay
A7: ORD-1006 | B7: 45205 | C7: Direct Online | D7: SKU-105 | E7: {=_xlfn.XLOOKUP(D7, Lookup_Dimensions!$A$2:$A$8, Lookup_Dimensions!$B$2:$B$8, "Unknown")} -> Logistics & Gear | F7: 1 | G7: 54.99 | H7: {=_xlfn.XLOOKUP(D7, Lookup_Dimensions!$A$2:$A$8, Lookup_Dimensions!$D$2:$D$8, 0)} -> 22 | I7: 0 | J7: Shipped | K7: REG-ALX | L7: 3 | M7: {=_xlfn.XLOOKUP(K7, Lookup_Dimensions!$H$2:$H$5, Lookup_Dimensions!$J$2:$J$5, 0)} -> 3 | N7: =L7-M7 -> 0 | O7: =IF(J7="Returned", 0, F7*G7 - I7) -> 54.99 | P7: =O7 - (F7*H7) -> 32.99 | Q7: In transit
A8: ORD-1007 | B8: 45206 | C8: B2B Wholesale | D8: SKU-101 | E8: {=_xlfn.XLOOKUP(D8, Lookup_Dimensions!$A$2:$A$8, Lookup_Dimensions!$B$2:$B$8, "Unknown")} -> Electronics | F8: 20 | G8: 39.99 | H8: {=_xlfn.XLOOKUP(D8, Lookup_Dimensions!$A$2:$A$8, Lookup_Dimensions!$D$2:$D$8, 0)} -> 18.5 | I8: 50 | J8: Delivered | K8: REG-CAI | L8: 1 | M8: {=_xlfn.XLOOKUP(K8, Lookup_Dimensions!$H$2:$H$5, Lookup_Dimensions!$J$2:$J$5, 0)} -> 2 | N8: =L8-M8 -> -1 | O8: =IF(J8="Returned", 0, F8*G8 - I8) -> 749.8 | P8: =O8 - (F8*H8) -> 379.8 | Q8: VIP Client
A9: ORD-1008 | B9: 45207 | C9: Marketplace | D9: SKU-106 | E9: {=_xlfn.XLOOKUP(D9, Lookup_Dimensions!$A$2:$A$8, Lookup_Dimensions!$B$2:$B$8, "Unknown")} -> Logistics & Gear | F9: 2 | G9: 22.5 | H9: {=_xlfn.XLOOKUP(D9, Lookup_Dimensions!$A$2:$A$8, Lookup_Dimensions!$D$2:$D$8, 0)} -> 9 | I9: 0 | J9: Delivered | K9: REG-CAN | L9: 5 | M9: {=_xlfn.XLOOKUP(K9, Lookup_Dimensions!$H$2:$H$5, Lookup_Dimensions!$J$2:$J$5, 0)} -> 4 | N9: =L9-M9 -> 1 | O9: =IF(J9="Returned", 0, F9*G9 - I9) -> 45 | P9: =O9 - (F9*H9) -> 27 | Q9: Missed SLA
A10: ORD-1009 | B10: 45208 | C10: Direct Online | D10: SKU-102 | E10: {=_xlfn.XLOOKUP(D10, Lookup_Dimensions!$A$2:$A$8, Lookup_Dimensions!$B$2:$B$8, "Unknown")} -> Electronics | F10: 1 | G10: 89.99 | H10: {=_xlfn.XLOOKUP(D10, Lookup_Dimensions!$A$2:$A$8, Lookup_Dimensions!$D$2:$D$8, 0)} -> 42 | I10: 15 | J10: Returned | K10: REG-UPP | L10: 5 | M10: {=_xlfn.XLOOKUP(K10, Lookup_Dimensions!$H$2:$H$5, Lookup_Dimensions!$J$2:$J$5, 0)} -> 5 | N10: =L10-M10 -> 0 | O10: =IF(J10="Returned", 0, F10*G10 - I10) -> 0 | P10: =O10 - (F10*H10) -> -42 | Q10: Defective item
A11: ORD-1010 | B11: 45209 | C11: B2B Wholesale | D11: SKU-107 | E11: {=_xlfn.XLOOKUP(D11, Lookup_Dimensions!$A$2:$A$8, Lookup_Dimensions!$B$2:$B$8, "Unknown")} -> Home & Storage | F11: 100 | G11: 34 | H11: {=_xlfn.XLOOKUP(D11, Lookup_Dimensions!$A$2:$A$8, Lookup_Dimensions!$D$2:$D$8, 0)} -> 14 | I11: 200 | J11: Delivered | K11: REG-ALX | L11: 3 | M11: {=_xlfn.XLOOKUP(K11, Lookup_Dimensions!$H$2:$H$5, Lookup_Dimensions!$J$2:$J$5, 0)} -> 3 | N11: =L11-M11 -> 0 | O11: =IF(J11="Returned", 0, F11*G11 - I11) -> 3200 | P11: =O11 - (F11*H11) -> 1800 | Q11: Restock order
A12: ORD-1011 | B12: 45210 | C12: Marketplace | D12: SKU-103 | E12: {=_xlfn.XLOOKUP(D12, Lookup_Dimensions!$A$2:$A$8, Lookup_Dimensions!$B$2:$B$8, "Unknown")} -> Apparel | F12: 2 | G12: 45 | H12: {=_xlfn.XLOOKUP(D12, Lookup_Dimensions!$A$2:$A$8, Lookup_Dimensions!$D$2:$D$8, 0)} -> 15 | I12: 0 | J12: Delivered | K12: REG-CAI | L12: 2 | M12: {=_xlfn.XLOOKUP(K12, Lookup_Dimensions!$H$2:$H$5, Lookup_Dimensions!$J$2:$J$5, 0)} -> 2 | N12: =L12-M12 -> 0 | O12: =IF(J12="Returned", 0, F12*G12 - I12) -> 90 | P12: =O12 - (F12*H12) -> 60 | Q12: On time
A13: ORD-1012 | B13: 45211 | C13: Direct Online | D13: SKU-104 | E13: {=_xlfn.XLOOKUP(D13, Lookup_Dimensions!$A$2:$A$8, Lookup_Dimensions!$B$2:$B$8, "Unknown")} -> Apparel | F13: 4 | G13: 24.99 | H13: {=_xlfn.XLOOKUP(D13, Lookup_Dimensions!$A$2:$A$8, Lookup_Dimensions!$D$2:$D$8, 0)} -> 8.5 | I13: 10 | J13: Shipped | K13: REG-CAN | L13: 4 | M13: {=_xlfn.XLOOKUP(K13, Lookup_Dimensions!$H$2:$H$5, Lookup_Dimensions!$J$2:$J$5, 0)} -> 4 | N13: =L13-M13 -> 0 | O13: =IF(J13="Returned", 0, F13*G13 - I13) -> 89.96 | P13: =O13 - (F13*H13) -> 55.96 | Q13: In transit
... A16: ORD-1015 | B16: 45214 | C16: B2B Wholesale | D16: SKU-102 | E16: {=_xlfn.XLOOKUP(D16, Lookup_Dimensions!$A$2:$A$8, Lookup_Dimensions!$B$2:$B$8, "Unknown")} -> Electronics | F16: 10 | G16: 89.99 | H16: {=_xlfn.XLOOKUP(D16, Lookup_Dimensions!$A$2:$A$8, Lookup_Dimensions!$D$2:$D$8, 0)} -> 42 | I16: 50 | J16: Delivered | K16: REG-CAI | L16: 2 | M16: {=_xlfn.XLOOKUP(K16, Lookup_Dimensions!$H$2:$H$5, Lookup_Dimensions!$J$2:$J$5, 0)} -> 2 | N16: =L16-M16 -> 0 | O16: =IF(J16="Returned", 0, F16*G16 - I16) -> 849.9 | P16: =O16 - (F16*H16) -> 429.9 | Q16: Corporate gift

Sheet Lookup_Dimensions
A1: SKU | B1: Category | C1: Product_Name | D1: Unit_Cost | E1: Standard_Price | F1: Supplier_Lead_Time_Days | H1: Region_Code | I1: Region_Name | J1: SLA_Target_Days | K1: Baseline_Shipping_Cost
A2: SKU-101 | B2: Electronics | C2: Wireless Ergonomic Mouse | D2: 18.5 | E2: 39.99 | F2: 5 | H2: REG-CAI | I2: Greater Cairo | J2: 2 | K2: 3.5
A3: SKU-102 | B3: Electronics | C3: Mechanical Keyboard | D3: 42 | E3: 89.99 | F3: 7 | H3: REG-ALX | I3: Alexandria & Delta | J3: 3 | K3: 4.5
A4: SKU-103 | B4: Apparel | C4: Performance Athletic Hoodie | D4: 15 | E4: 45 | F4: 10 | H4: REG-CAN | I4: Canal & Sinai | J4: 4 | K4: 6
A5: SKU-104 | B5: Apparel | C5: Breathable Training Shorts | D5: 8.5 | E5: 24.99 | F5: 10 | H5: REG-UPP | I5: Upper Egypt | J5: 5 | K5: 7.5
A6: SKU-105 | B6: Logistics & Gear | C6: Multi-Compartment Courier Bag | D6: 22 | E6: 54.99 | F6: 14
A7: SKU-106 | B7: Logistics & Gear | C7: High-Visibility LED Bike Lamp | D7: 9 | E7: 22.5 | F7: 14
A8: SKU-107 | B8: Home & Storage | C8: Modular Stackable Bins (4-Pack) | D8: 14 | E8: 34 | F8: 20
A11: Annotated Formula Guide: Data Hygiene & Lookups
A12: XLOOKUP / VLOOKUP: Used in Transactions_Model to pull Unit_Cost and Category based on SKU. Ensures consistency by centralizing product attributes, reducing manual entry errors.
A13: SUMIFS: Used in Executive_Dashboard to aggregate GMV and Net Profit by Channel. It allows for dynamic summarization without needing manual pivot table refreshes.
A14: IF Logic: Used to zero out Net Revenue for 'Returned' orders, ensuring accurate net calculations.
A15: Data Hygiene: Centralized dimension tables (Products, Regions) act as the source of truth, avoiding anomalies in raw operational data.

Sheet SQL_Pipeline_Documentation
A1: SQL Pipeline Documentation: Multi-Table E-Commerce Architecture
A3: CTE 1: Order_Turnaround_Base | B3: Extracts duration, date differences, and fulfillment SLA categorization.
A4: WITH Order_Turnaround_Base AS (
A5: SELECT Order_ID, Order_Date, Channel, Transit_Days,
A6: CASE WHEN Transit_Days <= SLA_Target_Days THEN 'On-Time' ELSE 'Delayed' END AS SLA_Status
A7: FROM raw_orders JOIN dim_regions ON raw_orders.Shipping_Region = dim_regions.Region_Code
A8: ),
A10: CTE 2: Customer_Order_History | B10: Uses window functions (DENSE_RANK) partitioned by state for customer lifetime aggregations.
A11: Customer_Order_History AS (
A12: SELECT Order_ID, Customer_ID, Shipping_Region,
A13: DENSE_RANK() OVER (PARTITION BY Shipping_Region ORDER BY Order_Date DESC) as regional_rank
A14: FROM Order_Turnaround_Base
A15: ),
A17: CTE 3: Corridor_Delay_Analysis | B17: Applies HAVING filters to identify state-level delay percentages.
A18: Corridor_Delay_Analysis AS (
A19: SELECT Shipping_Region, COUNT(*) as Total_Orders, SUM(CASE WHEN SLA_Status = 'Delayed' THEN 1 ELSE 0 END) / COUNT(*) as Delay_Rate
A20: FROM Order_Turnaround_Base GROUP BY Shipping_Region HAVING Delay_Rate > 0.1
A21: )
A23: Final Query & Strategic Output | B23: Joins CTEs to output the final actionable dataset for executive review.
A24: SELECT c.Shipping_Region, c.Delay_Rate, h.Customer_ID
A25: FROM Corridor_Delay_Analysis c
A26: LEFT JOIN Customer_Order_History h ON c.Shipping_Region = h.Shipping_Region
A27: WHERE h.regional_rank = 1;
